wurf/__init__.py
wurf/wurf.py
wurf-1.0.0.data/scripts/wurf
wurf-1.0.0.dist-info/LICENSE
wurf-1.0.0.dist-info/METADATA
wurf-1.0.0.dist-info/WHEEL
wurf-1.0.0.dist-info/top_level.txt
wurf-1.0.0.dist-info/RECORD
