Metadata-Version: 2.1
Name: wurf
Version: 1.0.0
Summary: Web Upload and Receive Files
Home-page: https://devcentral.nasqueron.org/source/wurf/
Author: Sébastien Santoro
Author-email: dereckson@espace-win.org
License: GPLv2+
Project-URL: Bug Tracker, https://devcentral.nasqueron.org/tag/wurf/
Classifier: Programming Language :: Python :: 3
Classifier: License :: OSI Approved :: GNU General Public License v2 or later (GPLv2+)
Classifier: Operating System :: OS Independent
Classifier: Environment :: Console
Classifier: Intended Audience :: Developers
Classifier: Intended Audience :: End Users/Desktop
Classifier: Intended Audience :: System Administrators
Classifier: Topic :: Communications :: File Sharing
Classifier: Topic :: Internet :: WWW/HTTP :: HTTP Servers
Requires-Python: >=3.6
License-File: LICENSE
